tuul_ai/__init__.py
tuul_ai/_base.py
tuul_ai/cli.py
tuul_ai/client.py
tuul_ai/exceptions.py
tuul_ai/resources/__init__.py
tuul_ai/resources/conversation.py
tuul_ai/resources/generative.py
tuul_ai/resources/lite.py
tuul_ai/types/__init__.py
tuul_ai/types/conversation.py
tuul_ai/types/generative.py
tuul_ai/types/lite.py
tuul_ai-0.1.0.dist-info/METADATA
tuul_ai-0.1.0.dist-info/WHEEL
tuul_ai-0.1.0.dist-info/entry_points.txt
tuul_ai-0.1.0.dist-info/RECORD
