Metadata-Version: 2.4
Name: tuul_ai
Version: 0.1.0
Summary: Official Python SDK for the Tuul API
Author-email: Dagbue Vivian <vivian@digitwhale.com>
License-Expression: MIT
Requires-Python: >=3.9
Requires-Dist: httpx>=0.25.0
Requires-Dist: pydantic>=2.0.0
Requires-Dist: rich>=13.0.0
Requires-Dist: typer>=0.9.0
Provides-Extra: dev
Requires-Dist: mypy>=1.6.0; extra == 'dev'
Requires-Dist: pytest-asyncio>=0.21; extra == 'dev'
Requires-Dist: pytest>=7.0; extra == 'dev'
Requires-Dist: respx>=0.20; extra == 'dev'
Requires-Dist: ruff>=0.1.0; extra == 'dev'
